locisimiles/__init__.py
locisimiles/cli.py
locisimiles/document.py
locisimiles/evaluator.py
locisimiles/pipeline/__init__.py
locisimiles/pipeline/_types.py
locisimiles/pipeline/classification.py
locisimiles/pipeline/retrieval.py
locisimiles/pipeline/two_stage.py
locisimiles_gui/__init__.py
locisimiles_gui/app.py
locisimiles_gui/config_stage.py
locisimiles_gui/results_stage.py
locisimiles_gui/upload_stage.py
locisimiles_gui/utils.py
locisimiles-0.3.5.dist-info/METADATA
locisimiles-0.3.5.dist-info/WHEEL
locisimiles-0.3.5.dist-info/entry_points.txt
locisimiles-0.3.5.dist-info/RECORD
