Metadata-Version: 2.3
Name: locisimiles
Version: 0.3.5
Summary: LociSimiles is a Python package for finding intertextual links in Latin literature using pre-trained language models.
Author: Julian Schelb
Author-email: julian.schelb@uni-konstanz.de
Requires-Python: >=3.10,<3.14
Classifier: Programming Language :: Python :: 3
Classifier: Programming Language :: Python :: 3.10
Classifier: Programming Language :: Python :: 3.11
Classifier: Programming Language :: Python :: 3.12
Classifier: Programming Language :: Python :: 3.13
Provides-Extra: gui
Requires-Dist: accelerate (>=0.20.0)
Requires-Dist: audioop-lts (>=0.2.1,<0.3.0) ; (python_version >= "3.13") and (extra == "gui")
Requires-Dist: chromadb (>=0.4.0,<2.0.0)
Requires-Dist: gradio (>=5.49.1) ; extra == "gui"
Requires-Dist: numpy (>=1.24.0,<3.0.0)
Requires-Dist: pandas (>=2.0.0,<3.0.0)
Requires-Dist: pydantic (==2.10.6) ; extra == "gui"
Requires-Dist: sentence-transformers (>=3.0.0,<6.0.0)
Requires-Dist: torch (>=2.0.0,<3.0.0)
Requires-Dist: transformers (>=4.30.0,<5.0.0)
